ytSearch/__init__.py
ytSearch/playlist.py
ytSearch/search.py
ytSearch/core/constants.py
ytSearch/core/handlers.py
ytSearch/core/requests.py
ytSearch/core/search.py
yt_search_py-1.0.0.dist-info/licenses/LICENSE
yt_search_py-1.0.0.dist-info/METADATA
yt_search_py-1.0.0.dist-info/WHEEL
yt_search_py-1.0.0.dist-info/top_level.txt
yt_search_py-1.0.0.dist-info/RECORD
