Metadata-Version: 2.4
Name: yt-search-py
Version: 1.0.0
Summary: Lightweight YouTube search library with async support - Search for videos, channels, playlists and get playlist details
Author-email: Sparrow <108956698+sparrow9616@users.noreply.github.com>
License: MIT
Project-URL: Homepage, https://github.com/sparrow9616/yt-search
Project-URL: Documentation, https://github.com/sparrow9616/yt-search/blob/main/README.md
Project-URL: Repository, https://github.com/sparrow9616/yt-search
Project-URL: Bug Tracker, https://github.com/sparrow9616/yt-search/issues
Keywords: youtube,search,youtube-search,playlist,async,youtube-api
Classifier: Development Status :: 4 - Beta
Classifier: Intended Audience :: Developers
Classifier: License :: OSI Approved :: MIT License
Classifier: Programming Language :: Python :: 3.8
Classifier: Programming Language :: Python :: 3.9
Classifier: Programming Language :: Python :: 3.10
Classifier: Programming Language :: Python :: 3.11
Classifier: Programming Language :: Python :: 3.12
Classifier: Programming Language :: Python :: 3.13
Classifier: Operating System :: OS Independent
Classifier: Topic :: Software Development :: Libraries :: Python Modules
Classifier: Topic :: Multimedia :: Video
Classifier: Topic :: Internet :: WWW/HTTP :: Dynamic Content
Requires-Python: >=3.7
License-File: LICENSE
Requires-Dist: httpx>=0.28.1
Dynamic: license-file
